lab_assistant_utils/__init__.py
lab_assistant_utils/cli.py
lab_assistant_utils/command_builder.py
lab_assistant_utils/docker.py
lab_assistant_utils/kernel_cli.py
lab_assistant_utils/kernel_launcher.py
lab_assistant_utils/utils.py
lab_assistant_utils/overrides/__init__.py
lab_assistant_utils/overrides/build_image_override.py
lab_assistant_utils/overrides/start_kernel_override.py
lab_assistant_utils-0.5.23.dist-info/LICENSE.md
lab_assistant_utils-0.5.23.dist-info/METADATA
lab_assistant_utils-0.5.23.dist-info/WHEEL
lab_assistant_utils-0.5.23.dist-info/entry_points.txt
lab_assistant_utils-0.5.23.dist-info/top_level.txt
lab_assistant_utils-0.5.23.dist-info/RECORD
