Metadata-Version: 2.1
Name: lab-assistant-utils
Version: 0.5.23
Summary: Lab Assistant Utilities
Home-page: https://github.com/enclarify/lab-assistant
Author: Anthony Schexnaildre
Author-email: aps@enclarify.com
License: UNKNOWN
Project-URL: Bug Tracker, https://github.com/enclarify/lab-assistant/issues
Platform: UNKNOWN
Classifier: Programming Language :: Python :: 3
Classifier: License :: OSI Approved :: MIT License
Classifier: Operating System :: OS Independent
Requires-Python: >=3.6
License-File: LICENSE.md
Requires-Dist: pytz (==2021.1)
Requires-Dist: click (==8.0.1)
Requires-Dist: docker (==5.0.3)
Requires-Dist: importlib-metadata (==4.6.3)
Requires-Dist: astpretty (==2.1.0)
Requires-Dist: ipykernel (==6.4.2)
Requires-Dist: docstring-parser (==0.13)
